{
    "prompts": ["a painting of a potato"],
    "image_prompts": [],
    "max_iterations": 350,
    "save_freq": 50,
    "size": [256, 256],
    "init_image": "",
    "init_noise": "",
    "init_weight": 0.0,
    "clip_model": "./models/ViT-B-32.pt",
    "vqgan_checkpoint": "./models/vqgan_imagenet_f16_16384.ckpt",
    "vqgan_config": "./configs/models/vqgan_imagenet_f16_16384.json",
    "noise_prompt_seeds": [],
    "noise_prompt_weights": [],
    "step_size": 0.1,
    "cutn": 32,
    "cut_pow": 1.0,
    "seed": 42,
    "optimizer": "Adam",
    "augments": ["Af", "Pe", "Ji", "Er"]
}
